mdpw/__init__.py
mdpw/drums.py
mdpw/instruments.py
mdpw-0.0.3.dist-info/METADATA
mdpw-0.0.3.dist-info/WHEEL
mdpw-0.0.3.dist-info/top_level.txt
mdpw-0.0.3.dist-info/RECORD
