Metadata-Version: 2.1
Name: mdpw
Version: 0.0.3
Summary: Generate MIDI file from Array of Array data.
Home-page: http://github.com/cwbp/mdpw
Author: cwbp
Author-email: cwbp@cwbp.com
License: MIT
Keywords: MIDI
Platform: UNKNOWN
Classifier: Development Status :: 3 - Alpha
Classifier: License :: OSI Approved :: MIT License
Classifier: Programming Language :: Python
Classifier: Programming Language :: Python :: 3
Classifier: Programming Language :: Python :: 3.6
Classifier: Programming Language :: Python :: 3.10
Classifier: Topic :: Multimedia :: Sound/Audio :: MIDI
Requires-Dist: pretty-midi
